local_qwen3b_part017/__init__.py
local_qwen3b_part017/qwen2.5-3b-instruct-q5_k_m.gguf.part_017
local_qwen3b_part017-0.0.1.dist-info/METADATA
local_qwen3b_part017-0.0.1.dist-info/WHEEL
local_qwen3b_part017-0.0.1.dist-info/top_level.txt
local_qwen3b_part017-0.0.1.dist-info/RECORD
